gp/recipe/node/README.rst
gp/recipe/node/__init__.py
gp/recipe/node/script.py
gp_recipe_node-22.17.1.1.dist-info/METADATA
gp_recipe_node-22.17.1.1.dist-info/WHEEL
gp_recipe_node-22.17.1.1.dist-info/entry_points.txt
gp_recipe_node-22.17.1.1.dist-info/top_level.txt
gp_recipe_node-22.17.1.1.dist-info/RECORD
