Metadata-Version: 2.4
Name: gp.recipe.node
Version: 22.17.1.1
Summary: ZC Buildout recipe for node.js
Home-page: https://github.com/gawel/gp.recipe.node
Author: Gael Pasgrimaud
Author-email: gael@gawel.org
License: ZPL
Keywords: buildout node.js node
Classifier: Framework :: Buildout
Classifier: Intended Audience :: Developers
Classifier: Topic :: Software Development :: Build Tools
Classifier: License :: OSI Approved :: Zope Public License
Classifier: Development Status :: 6 - Mature
Classifier: Programming Language :: Python :: 3.9
Classifier: Programming Language :: Python :: 3.10
Classifier: Programming Language :: Python :: 3.11
Classifier: Programming Language :: Python :: 3.12
Classifier: Programming Language :: Python :: 3.13
Requires-Python: >= 3.9
Requires-Dist: setuptools
Requires-Dist: zc.buildout
Requires-Dist: zc.recipe.egg
Requires-Dist: zc.recipe.cmmi
Provides-Extra: tests
Requires-Dist: zope.testing; extra == "tests"
Requires-Dist: zc.buildout; extra == "tests"
Dynamic: author
Dynamic: author-email
Dynamic: classifier
Dynamic: description
Dynamic: home-page
Dynamic: keywords
Dynamic: license
Dynamic: provides-extra
Dynamic: requires-dist
Dynamic: requires-python
Dynamic: summary
